{
    "batch": {
        "ExternalJobID": "2020240222105304462",
        "ExternalSystem": "ACCP",
        "ExternalTotalAmount": 1070,
        "ExternalCountTransaction": 1,
        "RejectAllRecords": false,
        "header": [
            {
                "INVOICE_ID": "20240222105304415",
                "InvoiceType": "Invoice",
                "InvoiceSubType": "3way",
                "Company": "98",
                "BU": "01",
                "SupplierNumber": "2",
                "SupplierSite": "BRE-BKK",
                "InvoiceNumber": "",
                "InvDate": "15/07/2024",
                "InvoiceCurrency": "THB",
                "InvAmtInclTax": 1070,
                "TaxAmount": 70,
                "InvoiceDescription": "test",
                "ExchRate": null,
                "ExchRateType": "USA",
                "ExchRateDate": "20/01/2024",
                "RefInvoice": null,
                "PaymentTerm": "IMMEDIATELY",
                "PaymentMethod": "Check",
                "PayGroup": "BANK DUE-BKK",
                "mockCurrentDate": "01/02/2025",
                "SupplierLiabilityAccount": null,
                "AccountDate": "04/04/2025",
                "CreatedBy": "",
                "line": [
                    {
                        "INVOICE_LINE_ID": "202402221053044170",
                        "INVOICE_ID": "20240222105304415",
                        "LineNo": 0,
                        "LineType": "",
                        "LineDescription": "",
                        "LineAmountInclTax": 1070,
                        "LineAmountExclTax": 1000,
                        "LineTaxAmount": 70,
                        "TaxRate": 0,
                        "TaxCode": "01.01.I.G",
                        "Withholding_Tax_Code_PAY": "01-00-01-20-AX",
                        "PONumber": "1234",
                        "POLineNumber": 0,
                        "GRNumber": "1234",
                        "GRLineNumber": 0,
                        "LineAccount": "01.01.00000.0000.14801.10003303.00000.000000.00000000",
                        "LineDiscountAmount": 0,
                        "CalDiscAllocation": 0,
                        "QTYInvoice": 0
                    }
                ]
            }
        ]
    }
}